hygen_add/__init__.py
hygen_add/hygen_add.py
hygen_add-0.1.0.dist-info/METADATA
hygen_add-0.1.0.dist-info/WHEEL
hygen_add-0.1.0.dist-info/entry_points.txt
hygen_add-0.1.0.dist-info/licenses/LICENSE
hygen_add-0.1.0.dist-info/RECORD
