Metadata-Version: 2.3
Name: hygen_add
Version: 0.1.0
Summary: Python version of the JS `hygen-add` project, which currently seems abandoned.
Project-URL: Homepage, https://github.com/italomaia/hygen-axum-podman-template
Project-URL: Issues, https://github.com/italomaia/hygen-axum-podman-template/issues
Author: Italo Maia
License-File: LICENSE
Classifier: License :: OSI Approved :: MIT License
Classifier: Operating System :: OS Independent
Classifier: Programming Language :: Python :: 3
Requires-Python: >=3.0
Requires-Dist: requests>=2
